{
  "indexes": [
    {
      "collectionGroup": "categories",
      "queryScope": "COLLECTION",
      "fields": [
        { "fieldPath": "displayOrder", "order": "ASCENDING" },
        { "fieldPath": "name", "order": "ASCENDING" }
      ]
    },
    {
      "collectionGroup": "categories",
      "queryScope": "COLLECTION",
      "fields": [
        { "fieldPath": "parentCategoryId", "order": "ASCENDING" },
        { "fieldPath": "displayOrder", "order": "ASCENDING" }
      ]
    },
    {
      "collectionGroup": "channels",
      "queryScope": "COLLECTION",
      "fields": [
        { "fieldPath": "status", "order": "ASCENDING" },
        { "fieldPath": "subscribers", "order": "DESCENDING" }
      ]
    },
    {
      "collectionGroup": "playlists",
      "queryScope": "COLLECTION",
      "fields": [
        { "fieldPath": "status", "order": "ASCENDING" },
        { "fieldPath": "itemCount", "order": "DESCENDING" }
      ]
    },
    {
      "collectionGroup": "videos",
      "queryScope": "COLLECTION",
      "fields": [
        { "fieldPath": "status", "order": "ASCENDING" },
        { "fieldPath": "uploadedAt", "order": "DESCENDING" }
      ]
    },
    {
      "collectionGroup": "audit_logs",
      "queryScope": "COLLECTION",
      "fields": [
        { "fieldPath": "actorUid", "order": "ASCENDING" },
        { "fieldPath": "timestamp", "order": "DESCENDING" }
      ]
    },
    {
      "collectionGroup": "audit_logs",
      "queryScope": "COLLECTION",
      "fields": [
        { "fieldPath": "entityType", "order": "ASCENDING" },
        { "fieldPath": "timestamp", "order": "DESCENDING" }
      ]
    },
    {
      "collectionGroup": "audit_logs",
      "queryScope": "COLLECTION",
      "fields": [
        { "fieldPath": "action", "order": "ASCENDING" },
        { "fieldPath": "timestamp", "order": "DESCENDING" }
      ]
    }
  ],
  "fieldOverrides": []
}

